nbgitpuller_downloader_googledrive/__init__.py
nbgitpuller_downloader_googledrive/googledrive_downloader.py
nbgitpuller_downloader_googledrive-0.1.0.dist-info/LICENSE
nbgitpuller_downloader_googledrive-0.1.0.dist-info/METADATA
nbgitpuller_downloader_googledrive-0.1.0.dist-info/WHEEL
nbgitpuller_downloader_googledrive-0.1.0.dist-info/entry_points.txt
nbgitpuller_downloader_googledrive-0.1.0.dist-info/top_level.txt
nbgitpuller_downloader_googledrive-0.1.0.dist-info/RECORD
