Metadata-Version: 2.1
Name: nbgitpuller-downloader-googledrive
Version: 0.1.0
Summary: Downloads compressed archives from Google Drive for nbgitpuller
Home-page: https://github.com/sean-morris/nbgitpuller-downloader-googledrive
Author: Sean Morris
Author-email: sean.smorris@berkeley.edu
License: UNKNOWN
Platform: UNKNOWN
Classifier: Programming Language :: Python :: 3
Classifier: License :: OSI Approved :: MIT License
Classifier: Operating System :: OS Independent
Requires-Python: >=3.8
License-File: LICENSE
